akimbo/__init__.py
akimbo/ak_from_cudf.py
akimbo/apply_tree.py
akimbo/cudf.py
akimbo/dask.py
akimbo/datetimes.py
akimbo/duck.py
akimbo/io.py
akimbo/mixin.py
akimbo/ops.py
akimbo/pandas.py
akimbo/polars.py
akimbo/py.typed
akimbo/ray.py
akimbo/spark.py
akimbo/strings.py
akimbo/utils.py
akimbo/version.py
akimbo-2025.3.0.dist-info/METADATA
akimbo-2025.3.0.dist-info/WHEEL
akimbo-2025.3.0.dist-info/licenses/LICENSE
akimbo-2025.3.0.dist-info/RECORD
